fab/__init__.py
fab/artefacts.py
fab/build_config.py
fab/cli.py
fab/constants.py
fab/dep_tree.py
fab/metrics.py
fab/mo.py
fab/tools.py
fab/util.py
fab/parse/__init__.py
fab/parse/c.py
fab/parse/fortran.py
fab/parse/fortran_common.py
fab/parse/x90.py
fab/steps/__init__.py
fab/steps/analyse.py
fab/steps/archive_objects.py
fab/steps/c_pragma_injector.py
fab/steps/cleanup_prebuilds.py
fab/steps/compile_c.py
fab/steps/compile_fortran.py
fab/steps/find_source_files.py
fab/steps/link.py
fab/steps/preprocess.py
fab/steps/psyclone.py
fab/steps/root_inc_files.py
fab/steps/grab/__init__.py
fab/steps/grab/archive.py
fab/steps/grab/fcm.py
fab/steps/grab/folder.py
fab/steps/grab/git.py
fab/steps/grab/prebuild.py
fab/steps/grab/svn.py
sci_fab-1.0.dist-info/LICENSE
sci_fab-1.0.dist-info/METADATA
sci_fab-1.0.dist-info/WHEEL
sci_fab-1.0.dist-info/entry_points.txt
sci_fab-1.0.dist-info/top_level.txt
sci_fab-1.0.dist-info/RECORD
