Metadata-Version: 2.1
Name: sci-fab
Version: 1.0
Summary: Build system for scientific software
Home-page: https://github.com/Metomi/fab
Author: SciFab Developers
Author-email: metomi@metoffice.gov.uk
License: UNKNOWN
Project-URL: Bug reports, https://github.com/metomi/fab/issues
Project-URL: Source, https://github.com/metomi/fab/
Platform: UNKNOWN
Classifier: Development Status :: 1 - Planning
Classifier: Environment :: Console
Classifier: License :: OSI Approved :: BSD License
Classifier: Operating System :: POSIX
Classifier: Programming Language :: Python :: 3
Classifier: Topic :: Scientific/Engineering
Classifier: Topic :: Software Development :: Build Tools
Requires-Python: >=3.7, <4
Requires-Dist: fparser
Provides-Extra: dev
Requires-Dist: pytest ; extra == 'dev'
Requires-Dist: pytest-cov ; extra == 'dev'
Requires-Dist: pytest-mock ; extra == 'dev'
Requires-Dist: flake8 ; extra == 'dev'
Requires-Dist: mypy ; extra == 'dev'
Requires-Dist: sphinx ; extra == 'dev'
Requires-Dist: sphinx-material ; extra == 'dev'
Requires-Dist: sphinx-autodoc-typehints ; extra == 'dev'
Requires-Dist: sphinx-copybutton ; extra == 'dev'
Requires-Dist: matplotlib ; extra == 'dev'
Requires-Dist: jinja2 ; extra == 'dev'
Requires-Dist: psyclone ; extra == 'dev'
Provides-Extra: docs
Requires-Dist: sphinx ; extra == 'docs'
Requires-Dist: sphinx-material ; extra == 'docs'
Requires-Dist: sphinx-autodoc-typehints ; extra == 'docs'
Requires-Dist: sphinx-copybutton ; extra == 'docs'
Provides-Extra: features
Requires-Dist: matplotlib ; extra == 'features'
Requires-Dist: jinja2 ; extra == 'features'
Requires-Dist: psyclone ; extra == 'features'
Provides-Extra: tests
Requires-Dist: pytest ; extra == 'tests'
Requires-Dist: pytest-cov ; extra == 'tests'
Requires-Dist: pytest-mock ; extra == 'tests'
Requires-Dist: flake8 ; extra == 'tests'
Requires-Dist: mypy ; extra == 'tests'
